README.md
setup.py
quantum_volume/__init__.py
quantum_volume/version.py
quantum_volume.egg-info/PKG-INFO
quantum_volume.egg-info/SOURCES.txt
quantum_volume.egg-info/dependency_links.txt
quantum_volume.egg-info/not-zip-safe
quantum_volume.egg-info/top_level.txt