Metadata-Version: 1.1
Name: quantum-volume
Version: 0.0.1
Summary: Quantum volume
Home-page: UNKNOWN
Author: Paul Nation
Author-email: paul.nation@ibm.com
License: Apache 2.0
Platform: UNKNOWN
Classifier: Environment :: Web Environment
Classifier: License :: OSI Approved :: Apache Software License
Classifier: Intended Audience :: Developers
Classifier: Intended Audience :: Science/Research
Classifier: Operating System :: Microsoft :: Windows
Classifier: Operating System :: MacOS
Classifier: Operating System :: POSIX :: Linux
Classifier: Programming Language :: Python :: 3.5
Classifier: Programming Language :: Python :: 3.6
Classifier: Programming Language :: Python :: 3.7
Classifier: Programming Language :: Python :: 3.8
Classifier: Topic :: Scientific/Engineering
